README
setup.py
cepfacil/__init__.py
cepfacil/models.py
cepfacil/urls.py
cepfacil/views.py
django_cepfacil.egg-info/PKG-INFO
django_cepfacil.egg-info/SOURCES.txt
django_cepfacil.egg-info/dependency_links.txt
django_cepfacil.egg-info/requires.txt
django_cepfacil.egg-info/top_level.txt