Metadata-Version: 1.0
Name: django-cepfacil
Version: 0.0.1
Summary: A Django app that provides a wrapper to CEP Fácil web service.
Home-page: https://github.com/adonescunha/django-cepfacil/
Author: Adones Cunha
Author-email: hi@adonescunha.com
License: UNKNOWN
Platform: UNKNOWN
Classifier: Development Status :: 1 - Planning
Classifier: Environment :: Web Environment
Classifier: Intended Audience :: Developers
Classifier: License :: OSI Approved :: MIT License
Classifier: Operating System :: OS Independent
Classifier: Programming Language :: Python
Classifier: Framework :: Django
Classifier: Topic :: Utilities
